odoo/addons/l10n_fr_siret_account/README.rst
odoo/addons/l10n_fr_siret_account/__init__.py
odoo/addons/l10n_fr_siret_account/__manifest__.py
odoo/addons/l10n_fr_siret_account/i18n/l10n_fr_siret_account.pot
odoo/addons/l10n_fr_siret_account/models/__init__.py
odoo/addons/l10n_fr_siret_account/models/res_partner.py
odoo/addons/l10n_fr_siret_account/readme/CONTRIBUTORS.md
odoo/addons/l10n_fr_siret_account/readme/DESCRIPTION.md
odoo/addons/l10n_fr_siret_account/static/description/icon.png
odoo/addons/l10n_fr_siret_account/static/description/index.html
odoo/addons/l10n_fr_siret_account/views/res_partner.xml
odoo_addon_l10n_fr_siret_account-18.0.1.0.0.2.dist-info/METADATA
odoo_addon_l10n_fr_siret_account-18.0.1.0.0.2.dist-info/WHEEL
odoo_addon_l10n_fr_siret_account-18.0.1.0.0.2.dist-info/top_level.txt
odoo_addon_l10n_fr_siret_account-18.0.1.0.0.2.dist-info/RECORD
